[{"Combination": 1, "Learning Rate": 0.0001, "Batch Size": 32, "Dropout": 0.5, "Dense": 512, "Augmentation": false, "Base Model Trainable": true, "Growth Rate": 16, "Blocks": 4, "Activation": "swish", "Train Accuracy": 0.9697933197021484, "Val Accuracy": 0.8855721354484558, "Test Accuracy": 0.9170731902122498}, {"Combination": 2, "Learning Rate": 0.0001, "Batch Size": 32, "Dropout": 0.5, "Dense": 128, "Augmentation": true, "Base Model Trainable": true, "Growth Rate": 32, "Blocks": 4, "Activation": "relu", "Train Accuracy": 0.9374668598175049, "Val Accuracy": 0.8557214140892029, "Test Accuracy": 0.9097561240196228}, {"Combination": 3, "Learning Rate": 0.01, "Batch Size": 64, "Dropout": 0.5, "Dense": 256, "Augmentation": true, "Base Model Trainable": true, "Growth Rate": 32, "Blocks": 5, "Activation": "swish", "Train Accuracy": 0.6968733668327332, "Val Accuracy": 0.6169154047966003, "Test Accuracy": 0.6414633989334106}, {"Combination": 4, "Learning Rate": 0.01, "Batch Size": 64, "Dropout": 0.2, "Dense": 512, "Augmentation": false, "Base Model Trainable": false, "Growth Rate": 16, "Blocks": 4, "Activation": "relu", "Train Accuracy": 0.9083200693130493, "Val Accuracy": 0.8457711338996887, "Test Accuracy": 0.8951219320297241}, {"Combination": 5, "Learning Rate": 0.01, "Batch Size": 32, "Dropout": 0.5, "Dense": 128, "Augmentation": true, "Base Model Trainable": true, "Growth Rate": 32, "Blocks": 5, "Activation": "relu", "Train Accuracy": 0.6126126050949097, "Val Accuracy": 0.611940324306488, "Test Accuracy": 0.6121951341629028}, {"Combination": 6, "Learning Rate": 0.001, "Batch Size": 16, "Dropout": 0.3, "Dense": 128, "Augmentation": false, "Base Model Trainable": true, "Growth Rate": 32, "Blocks": 5, "Activation": "swish", "Train Accuracy": 0.8595654368400574, "Val Accuracy": 0.676616907119751, "Test Accuracy": 0.787804901599884}, {"Combination": 7, "Learning Rate": 0.01, "Batch Size": 32, "Dropout": 0.5, "Dense": 256, "Augmentation": true, "Base Model Trainable": false, "Growth Rate": 16, "Blocks": 3, "Activation": "relu", "Train Accuracy": 0.8129305839538574, "Val Accuracy": 0.8059701323509216, "Test Accuracy": 0.8853658437728882}, {"Combination": 8, "Learning Rate": 0.001, "Batch Size": 32, "Dropout": 0.5, "Dense": 256, "Augmentation": true, "Base Model Trainable": true, "Growth Rate": 32, "Blocks": 4, "Activation": "relu", "Train Accuracy": 0.8118706941604614, "Val Accuracy": 0.6517412662506104, "Test Accuracy": 0.785365879535675}, {"Combination": 9, "Learning Rate": 0.0001, "Batch Size": 32, "Dropout": 0.2, "Dense": 512, "Augmentation": false, "Base Model Trainable": false, "Growth Rate": 16, "Blocks": 3, "Activation": "relu", "Train Accuracy": 0.9284578561782837, "Val Accuracy": 0.8681591749191284, "Test Accuracy": 0.8902438879013062}, {"Combination": 10, "Learning Rate": 0.0001, "Batch Size": 32, "Dropout": 0.2, "Dense": 256, "Augmentation": true, "Base Model Trainable": true, "Growth Rate": 16, "Blocks": 3, "Activation": "swish", "Train Accuracy": 0.9395866394042969, "Val Accuracy": 0.8681591749191284, "Test Accuracy": 0.9170731902122498}]